trackingmore/__init__.py
trackingmore/tracker.py
trackingmore/classes/__init__.py
trackingmore/classes/api.py
trackingmore_api_tool-0.1.2.dist-info/METADATA
trackingmore_api_tool-0.1.2.dist-info/WHEEL
trackingmore_api_tool-0.1.2.dist-info/entry_points.txt
trackingmore_api_tool-0.1.2.dist-info/licenses/LICENSE
trackingmore_api_tool-0.1.2.dist-info/RECORD
