Metadata-Version: 2.3
Name: trackingmore-api-tool
Version: 0.1.2
Summary: API wrapper for the TrackingMore API (v3)
Project-URL: Homepage, https://kumig.it/kumitterer/trackingmore-api-tool
Project-URL: Bug Tracker, https://kumig.it/kumitterer/trackingmore-api-tool/issues
Author-email: Kumi Mitterer <trackingmore-api-tool@kumi.email>
License: Copyright (c) 2023 Kumi Mitterer <trackingmore-api-tool@kumi.email>
License-File: LICENSE
Classifier: License :: OSI Approved :: MIT License
Classifier: Operating System :: OS Independent
Classifier: Programming Language :: Python :: 3
Requires-Python: >=3.8
